amberflow_db/__init__.py
amberflow_db/database.py
amberflow_db-0.1.15.dist-info/METADATA
amberflow_db-0.1.15.dist-info/WHEEL
amberflow_db-0.1.15.dist-info/top_level.txt
amberflow_db-0.1.15.dist-info/RECORD
