Metadata-Version: 2.4
Name: amberflow-db
Version: 0.1.15
Summary: The database for AmberFlow
Author: AmberFlow
Requires-Dist: sqlalchemy>=2.0.0
Requires-Dist: psycopg2-binary>=2.9.0
Dynamic: author
Dynamic: requires-dist
Dynamic: summary
